gcrnet/__init__.py
gcrnet/gcrnet.py
gcrnet/losses.py
gcrnet/mlp.py
gcrnet/models.py
gcrnet/penalty.py
gcrnet/utils.py
gcrnet-1.1.0.dist-info/LICENSE
gcrnet-1.1.0.dist-info/METADATA
gcrnet-1.1.0.dist-info/WHEEL
gcrnet-1.1.0.dist-info/top_level.txt
gcrnet-1.1.0.dist-info/RECORD
