Metadata-Version: 2.1
Name: gcrnet
Version: 1.1.0
Summary: A Python library for sparse-input neural networks using group concave regularization
Author: Bin Luo
Author-email: bluo@kennesaw.edu
License: MIT
License-File: LICENSE
Requires-Dist: torch
Requires-Dist: numpy
Requires-Dist: six
Requires-Dist: scipy
Requires-Dist: scikit-learn
Requires-Dist: lifelines
Requires-Dist: matplotlib
Requires-Dist: joblib
Requires-Dist: pandas
